earcut/__init__.py
earcut/utils_3d.py
earcut_py-0.3.1.dist-info/METADATA
earcut_py-0.3.1.dist-info/WHEEL
earcut_py-0.3.1.dist-info/licenses/LICENSE.txt
earcut_py-0.3.1.dist-info/RECORD
