Metadata-Version: 2.3
Name: earcut-py
Version: 0.3.1
Summary: A pure Python port of the Earcut polygon triangulation library.
Author-email: "MIERUNE Inc." <info@mierune.co.jp>, Taku Fukada <naninunenor@gmail.com>
License-File: LICENSE.txt
Requires-Python: >=3.9
